Workbook

Sheet PLANIFICACION
A1: NOMBRE DEL PROYECTO | B1: POSEIDÓN – Sistema Web del Club Náutico Poseidón del Perú
A2: DESCRIPCIÓN: | B2: Sistema web para la gestión de socios, embarcaciones, salidas de naves, facturación y cobranzas del club.
A3: RESPONSABLE DEL PROYECTO | B3: =EQUIPO!$B$7 -> Jose Espinoza Rivadeneira
A5: Épicas | B5: Sprint | C5: Historias de Usuario | D5: Criterios de aceptación | E5: Estado | F5: Tecnologías utilizadas | G5: Inicio y Fin | H5: Recurso Responsable | I5: Release
A6: Home Page y Base del Sistema Web: Establecer la base técnica del proyecto y publicar la página de inicio (Home) del Club Náutico Poseidón del Perú. | B6: 1 | C6: HU01 - Configuración del proyecto y control de versiones Como equipo de desarrollo quiero configurar el proyecto Angular, los estilos y los repositorios para trabajar de forma ordenada y con trazabilidad de cambios. | D6: Proyecto Angular creado con Angular CLI y estructura de carpetas (components, pages, services, assets) | E6: Completado | F6: Angular CLI, TypeScript, Node.js. Bootstrap 5, SCSS. Git, GitHub, Visual Studio Code. Jira (backlog exportado a Excel). | G6: 19/09/26 al 25/09/26 | H6: =EQUIPO!$B$7 -> Jose Espinoza Rivadeneira | I6: Versión 1: Home page y acceso al sistema
B7: 1 | D7: Bootstrap 5 y SCSS configurados, con variables de color y tipografía en un archivo global | E7: Completado
B8: 1 | D8: Repositorio en GitHub con ramas main, develop y feature/*, y todos los integrantes agregados como colaboradores | E8: Completado
B9: 1 | D9: Backlog cargado en Jira y exportado a Excel | E9: Completado
B10: 1 | C10: HU02 - Barra de navegación y pie de página Como visitante quiero una barra de navegación clara y un pie de página para desplazarme fácilmente por el sitio del club. | D10: Navbar con logo y enlaces: Inicio, Nosotros, Servicios, Instalaciones y Contacto | E10: Completado | F10: Angular (componentes navbar y footer, RouterModule). Bootstrap 5 (Navbar), SCSS. | G10: 19/09/26 al 02/10/26 | H10: =EQUIPO!$B$7 -> Jose Espinoza Rivadeneira | I10: Versión 1: Home page y acceso al sistema
B11: 1 | D11: Menú colapsable (hamburguesa) en pantallas pequeñas | E11: En proceso
B12: 1 | D12: Botones "Hazte socio" e "Iniciar sesión" visibles en la barra | E12: Completado
B13: 1 | D13: Footer con datos de contacto, redes sociales y derechos reservados | E13: Completado
B14: 1 | C14: HU03 - Portada de bienvenida (Hero) Como visitante quiero ver una portada atractiva con la propuesta del club para saber de inmediato qué ofrece. | D14: Banner principal con imagen náutica (muelle o embarcaciones) y título de bienvenida | E14: Completado | F14: Angular (componente hero). Bootstrap 5 (grid, botones), SCSS. | G14: 26/09/26 al 02/10/26 | H14: =EQUIPO!$B$7 -> Jose Espinoza Rivadeneira | I14: Versión 1: Home page y acceso al sistema
B15: 1 | D15: Texto breve con la propuesta de valor del club | E15: Completado
B16: 1 | D16: Botones de acción: "Quiero ser socio" y "Conoce nuestros servicios" | E16: Completado
B17: 1 | D17: Imagen optimizada que no afecte la velocidad de carga | E17: Completado
B18: 1 | C18: HU04 - Secciones informativas del club Como visitante quiero conocer el club, sus servicios e instalaciones para decidir si me interesa inscribirme como socio. | D18: Sección "Nosotros" con reseña, misión y visión del club | E18: Completado | F18: Angular (componentes por sección). Bootstrap 5 (cards, grid), SCSS. | G18: 26/09/26 al 02/10/26 | H18: =EQUIPO!$B$8 -> Jack | I18: Versión 1: Home page y acceso al sistema
B19: 1 | D19: Sección "Servicios" en tarjetas: amarre de embarcaciones (rada), limpieza de nave, cabotaje, traslado de nave, cafetería e instructores de natación, navegación y buceo | E19: Completado
B20: 1 | D20: Sección "Instalaciones": piscinas, salones de relajación, cafeterías y salones de fiestas | E20: Completado
B21: 1 | D21: Al hacer clic en el menú, la página se desplaza a la sección correspondiente | E21: En proceso
B22: 1 | C22: HU05 - Contacto y diseño adaptable (responsive) Como visitante quiero contactar al club y ver el sitio correctamente desde mi celular para resolver mis dudas desde cualquier dispositivo. | D22: Sección de contacto con dirección, teléfono, correo y horario de atención | E22: Completado | F22: Angular (Reactive Forms). Bootstrap 5 (grid, breakpoints), SCSS (media queries). | G22: 26/09/26 al 02/10/26 | H22: =EQUIPO!$B$8 -> Jack | I22: Versión 1: Home page y acceso al sistema
B23: 1 | D23: Formulario de consulta con validación de campos (nombre, correo y mensaje) | E23: Completado
B24: 1 | D24: Referencia de ubicación del club (mapa o dirección) | E24: Falta
B25: 1 | D25: Home probado en móvil, tablet y escritorio sin desbordes de contenido | E25: En proceso
A26: Acceso al Sistema y Roles de Usuario: Permitir el ingreso seguro al sistema según el perfil de cada usuario del club. | B26: 2 | C26: HU06 - Inicio de sesión Como usuario del sistema (socio o personal del club) quiero iniciar sesión con mi usuario y contraseña para acceder a las funciones de mi perfil. | D26: Formulario de inicio de sesión con validación de campos obligatorios | E26: Falta | F26: Angular (RouterModule, Guards). Bootstrap 5, SCSS. Datos: API REST (por definir con el equipo). | G26: 03/10/26 al 09/10/26 | H26: =EQUIPO!$B$7 -> Jose Espinoza Rivadeneira | I26: Versión 1: Home page y acceso al sistema
B27: 2 | D27: Mensaje claro cuando las credenciales son incorrectas | E27: Falta
B28: 2 | D28: Sesión persistente y opción de cerrar sesión | E28: Falta
B29: 2 | D29: Recuperación de contraseña mediante correo electrónico | E29: Falta
B30: 2 | C30: HU07 - Roles y permisos Como Gerente General quiero que cada área acceda solo a sus funciones para mantener la seguridad de la información del club. | D30: Roles definidos: Gerente General, Atención al Cliente, Servicios Navieros, Administración y Socio | E30: Falta | F30: Angular (RouterModule, Guards). Bootstrap 5, SCSS. Datos: API REST (por definir con el equipo). | G30: 10/10/26 al 16/10/26 | H30: =EQUIPO!$B$8 -> Jack | I30: Versión 1: Home page y acceso al sistema
B31: 2 | D31: Menú de opciones distinto según el rol del usuario | E31: Falta
B32: 2 | D32: Rutas protegidas (guards) que impiden entrar a pantallas no autorizadas | E32: Falta
B33: 2 | D33: Redirección al panel correspondiente después de iniciar sesión | E33: Falta
A34: Inscripción y Aprobación de Socios: Digitalizar la solicitud, verificación y aprobación de nuevos socios, evitando dobles inscripciones. | B34: 3 | C34: HU08 - Solicitar inscripción como socio Como postulante quiero llenar la solicitud de inscripción en línea para iniciar mi proceso de ingreso al club. | D34: Formulario con datos personales, contacto y documento de identidad | E34: Falta | F34: Angular (Reactive Forms, RouterModule). Bootstrap 5, SCSS. Datos: API REST (por definir con el equipo). | G34: 17/10/26 al 23/10/26 | H34: =EQUIPO!$B$7 -> Jose Espinoza Rivadeneira | I34: Versión 2: Socios, embarcaciones y salidas
B35: 3 | D35: Campo para indicar si posee embarcaciones (no es obligatorio para ser socio) | E35: Falta
B36: 3 | D36: Validación de datos obligatorios y de formato (DNI, correo y teléfono) | E36: Falta
B37: 3 | D37: Constancia de registro de la solicitud con número de seguimiento | E37: Falta
B38: 3 | C38: HU09 - Verificar y clasificar al postulante Como secretaria de Atención al Cliente quiero verificar la solicitud y clasificar al postulante para que solo se acepten socios de tipo "pagador". | D38: Bandeja de solicitudes pendientes de verificación | E38: Falta | F38: Angular (Reactive Forms, RouterModule). Bootstrap 5, SCSS. Datos: API REST (por definir con el equipo). | G38: 17/10/26 al 30/10/26 | H38: =EQUIPO!$B$8 -> Jack | I38: Versión 2: Socios, embarcaciones y salidas
B39: 3 | D39: Alerta automática cuando el documento de identidad ya está registrado (evita la doble inscripción) | E39: Falta
B40: 3 | D40: Registro del resultado de la verificación con otros clubes | E40: Falta
B41: 3 | D41: Clasificación del postulante: pagador, pagador esporádico o renuente a pago | E41: Falta
B42: 3 | D42: Solo las solicitudes de tipo "pagador" pasan a la aprobación del Jefe | E42: Falta
B43: 3 | C43: HU10 - Aprobar o desaprobar solicitud Como Jefe de Atención al Cliente quiero aprobar o desaprobar solicitudes para incorporar únicamente a postulantes que cumplan la política del club. | D43: Bandeja de solicitudes verificadas pendientes de decisión | E43: Falta | F43: Angular (Reactive Forms, RouterModule). Bootstrap 5, SCSS. Datos: API REST (por definir con el equipo). | G43: 24/10/26 al 30/10/26 | H43: =EQUIPO!$B$7 -> Jose Espinoza Rivadeneira | I43: Versión 2: Socios, embarcaciones y salidas
B44: 3 | D44: Al aprobar, se otorga el rango de "Socio" y se activa su usuario | E44: Falta
B45: 3 | D45: Al desaprobar, es obligatorio registrar los motivos y se genera un documento descargable (PDF) para el postulante | E45: Falta
B46: 3 | D46: Notificación por correo al postulante con el resultado | E46: Falta
A47: Embarcaciones y Radas: Registrar las embarcaciones de los socios y asignar la rada (lugar de amarre) adecuada a cada una. | B47: 4 | C47: HU11 - Registrar embarcación Como socio quiero registrar mis embarcaciones en la ficha de "Registro de Embarcación" para que el club les asigne un lugar de amarre. | D47: Una ficha por cada embarcación (nombre, matrícula, tipo, eslora, manga y calado) | E47: Falta | F47: Angular (Reactive Forms, RouterModule). Bootstrap 5, SCSS. Datos: API REST (por definir con el equipo). | G47: 31/10/26 al 06/11/26 | H47: =EQUIPO!$B$8 -> Jack | I47: Versión 2: Socios, embarcaciones y salidas
B48: 4 | D48: Un socio puede registrar varias embarcaciones | E48: Falta
B49: 4 | D49: Carga de documentos de la nave (matrícula y certificados) | E49: Falta
B50: 4 | D50: Estado de la ficha visible para el socio: pendiente, verificada u observada | E50: Falta
B51: 4 | C51: HU12 - Verificar embarcación en Capitanías Como personal de Servicios Navieros quiero verificar los datos de la nave en los registros de la Dirección de Capitanías y Guardacostas para asegurar que la información es correcta. | D51: Bandeja de fichas pendientes de verificación | E51: Falta | F51: Angular (Reactive Forms, RouterModule). Bootstrap 5, SCSS. Datos: API REST (por definir con el equipo). | G51: 31/10/26 al 13/11/26 | H51: =EQUIPO!$B$7 -> Jose Espinoza Rivadeneira | I51: Versión 2: Socios, embarcaciones y salidas
B52: 4 | D52: Registro del resultado (conforme u observada) con sus observaciones | E52: Falta
B53: 4 | D53: Notificación al socio cuando la ficha es observada para que la subsane | E53: Falta
B54: 4 | D54: Solo las embarcaciones verificadas pueden asignarse a una rada | E54: Falta
B55: 4 | C55: HU13 - Asignar rada Como personal de Servicios Navieros quiero asignar la rada según el tamaño y características de la nave para aprovechar mejor los amarres disponibles. | D55: Listado de radas con su estado (libre u ocupada) y dimensiones | E55: Falta | F55: Angular (Reactive Forms, RouterModule). Bootstrap 5, SCSS. Datos: API REST (por definir con el equipo). | G55: 07/11/26 al 13/11/26 | H55: =EQUIPO!$B$8 -> Jack | I55: Versión 2: Socios, embarcaciones y salidas
B56: 4 | D56: Sugerencia de radas compatibles con las medidas de la embarcación | E56: Falta
B57: 4 | D57: Asignación y liberación de rada con historial de cambios | E57: Falta
B58: 4 | D58: Constancia de asignación disponible para el socio | E58: Falta
A59: Salidas de Embarcaciones: Controlar los permisos de salida de las naves para evitar demoras y retenciones por documentación incompleta. | B59: 5 | C59: HU14 - Solicitar permiso de salida Como socio quiero solicitar en línea el permiso de salida de mi embarcación para evitar demoras al navegar. | D59: Formulario con fecha de partida, fecha de retorno e itinerario de viaje | E59: Falta | F59: Angular (Reactive Forms, RouterModule). Bootstrap 5, SCSS. Datos: API REST (por definir con el equipo). | G59: 14/11/26 al 20/11/26 | H59: =EQUIPO!$B$7 -> Jose Espinoza Rivadeneira | I59: Versión 2: Socios, embarcaciones y salidas
B60: 5 | D60: Registro de las personas que abordarán la nave (nombre y documento) | E60: Falta
B61: 5 | D61: Selección de tripulación especializada registrada y autorizada | E61: Falta
B62: 5 | D62: Si el socio tiene cuotas vencidas, se muestra la deuda con su interés y se exige su pago antes de aprobar la salida | E62: Falta
B63: 5 | C63: HU15 - Validar documentación y aprobar salida Como personal de Servicios Navieros quiero validar los datos y documentos de cada salida para prevenir retenciones por parte de la autoridad marítima. | D63: Bandeja de solicitudes de salida pendientes | E63: Falta | F63: Angular (Reactive Forms, RouterModule). Bootstrap 5, SCSS. Datos: API REST (por definir con el equipo). | G63: 14/11/26 al 27/11/26 | H63: =EQUIPO!$B$8 -> Jack | I63: Versión 2: Socios, embarcaciones y salidas
B64: 5 | D64: Lista de verificación de documentos de la nave y de la tripulación | E64: Falta
B65: 5 | D65: Aprobación o rechazo con observaciones y notificación al socio | E65: Falta
B66: 5 | D66: Permiso confirmado con código de salida | E66: Falta
B67: 5 | C67: HU16 - Registrar salida y retorno Como personal de Servicios Navieros quiero registrar la salida y el retorno de las embarcaciones para mantener un control actualizado. | D67: Registro de fecha y hora de salida y de retorno por embarcación | E67: Falta | F67: Angular (Reactive Forms, RouterModule). Bootstrap 5, SCSS. Datos: API REST (por definir con el equipo). | G67: 21/11/26 al 27/11/26 | H67: =EQUIPO!$B$7 -> Jose Espinoza Rivadeneira | I67: Versión 2: Socios, embarcaciones y salidas
B68: 5 | D68: Alerta de embarcaciones con retorno vencido | E68: Falta
B69: 5 | D69: Historial de salidas por embarcación y por socio | E69: Falta
B70: 5 | D70: Reporte de salidas por rango de fechas | E70: Falta
A71: Servicios del Club y Facturación: Registrar los servicios usados por los socios y emitir la facturación mensual. | B71: 6 | C71: HU17 - Registrar servicios adicionales Como personal del club quiero registrar los servicios adicionales que usa un socio para incluirlos en su facturación. | D71: Catálogo de servicios con precio: limpieza de nave, cabotaje, traslado de nave, cafetería e instructores de natación, navegación y buceo | E71: Falta | F71: Angular (Reactive Forms, RouterModule). Bootstrap 5, SCSS. Datos: API REST (por definir con el equipo). | G71: 28/11/26 al 04/12/26 | H71: =EQUIPO!$B$8 -> Jack | I71: Versión 3: Facturación, cobranzas y reportes
B72: 6 | D72: Registro del servicio con fecha, socio y cantidad | E72: Falta
B73: 6 | D73: Consulta de los servicios registrados desde la cuenta del socio | E73: Falta
B74: 6 | D74: Anulación o edición con justificación antes del cierre del mes | E74: Falta
B75: 6 | C75: HU18 - Emitir facturación mensual Como Departamento de Facturación quiero emitir el recibo mensual de cada socio para cobrar la membresía, la rada y los servicios. | D75: Cálculo automático de membresía, rada por cada embarcación y servicios adicionales | E75: Falta | F75: Angular (Reactive Forms, RouterModule). Bootstrap 5, SCSS. Datos: API REST (por definir con el equipo). | G75: 28/11/26 al 11/12/26 | H75: =EQUIPO!$B$7 -> Jose Espinoza Rivadeneira | I75: Versión 3: Facturación, cobranzas y reportes
B76: 6 | D76: Recibo con detalle por rubro y total a pagar | E76: Falta
B77: 6 | D77: Emisión masiva mensual para todos los socios activos | E77: Falta
B78: 6 | D78: Descarga del recibo en PDF y envío por correo electrónico | E78: Falta
B79: 6 | C79: HU19 - Facturación diferida Como socio quiero pagar mis servicios en cuotas para distribuir mi gasto mensual. | D79: Solicitud de pago diferido sobre los servicios del mes | E79: Falta | F79: Angular (Reactive Forms, RouterModule). Bootstrap 5, SCSS. Datos: API REST (por definir con el equipo). | G79: 05/12/26 al 11/12/26 | H79: =EQUIPO!$B$8 -> Jack | I79: Versión 3: Facturación, cobranzas y reportes
B80: 6 | D80: Máximo de 6 cuotas mensuales, validado en el formulario | E80: Falta
B81: 6 | D81: Cronograma de cuotas con fechas y montos | E81: Falta
B82: 6 | D82: Las cuotas se incluyen en los recibos de los meses siguientes | E82: Falta
A83: Cobranzas y Retiro de Socios: Controlar los pagos y la morosidad, y gestionar el retiro formal de socios del club. | B83: 7 | C83: HU20 - Registrar pagos e intereses por mora Como Departamento de Cobranzas quiero registrar los pagos y calcular los intereses por atraso para mantener al día las cuentas de los socios. | D83: Registro de pago con fecha, monto y medio de pago | E83: Falta | F83: Angular (Reactive Forms, RouterModule). Bootstrap 5, SCSS. Datos: API REST (por definir con el equipo). | G83: 12/12/26 al 25/12/26 | H83: =EQUIPO!$B$7 -> Jose Espinoza Rivadeneira | I83: Versión 3: Facturación, cobranzas y reportes
B84: 7 | D84: Cálculo automático del interés moratorio con la tasa bancaria de referencia de la SBS (tasa configurable) | E84: Falta
B85: 7 | D85: Estado de cuenta por socio con deuda, intereses y pagos realizados | E85: Falta
B86: 7 | D86: Aviso de deuda pendiente cuando el socio solicita usar su embarcación | E86: Falta
B87: 7 | C87: HU21 - Solicitar retiro del club Como socio quiero presentar mi solicitud de retiro en línea para dejar de pertenecer al club. | D87: Formulario de "Solicitud de Retiro" con el motivo del retiro | E87: Falta | F87: Angular (Reactive Forms, RouterModule). Bootstrap 5, SCSS. Datos: API REST (por definir con el equipo). | G87: 12/12/26 al 18/12/26 | H87: =EQUIPO!$B$8 -> Jack | I87: Versión 3: Facturación, cobranzas y reportes
B88: 7 | D88: Constancia de recepción de la solicitud | E88: Falta
B89: 7 | D89: Seguimiento del estado de la solicitud por el socio | E89: Falta
B90: 7 | D90: Notificación al área de Atención al Cliente | E90: Falta
B91: 7 | C91: HU22 - Liquidación administrativa y baja de socio Como Atención al Cliente quiero generar la liquidación administrativa del socio que se retira para cobrar sus pagos pendientes antes de darlo de baja. | D91: Liquidación automática con cuotas, intereses, servicios y radas pendientes | E91: Falta | F91: Angular (Reactive Forms, RouterModule). Bootstrap 5, SCSS. Datos: API REST (por definir con el equipo). | G91: 19/12/26 al 25/12/26 | H91: =EQUIPO!$B$7 -> Jose Espinoza Rivadeneira | I91: Versión 3: Facturación, cobranzas y reportes
B92: 7 | D92: Documento de liquidación descargable en PDF | E92: Falta
B93: 7 | D93: Baja del socio solo cuando su deuda es cero | E93: Falta
B94: 7 | D94: El socio dado de baja queda en el histórico (no se elimina) | E94: Falta
A95: Atención al Cliente y Reportes Gerenciales: Gestionar las quejas de los socios y brindar información para la toma de decisiones. | B95: 8 | C95: HU23 - Registrar y atender quejas Como socio quiero registrar una queja o reclamo para que el club atienda mi problema. | D95: Formulario de queja con categoría, descripción y adjuntos | E95: Falta | F95: Angular (Reactive Forms, RouterModule). Bootstrap 5, SCSS. Datos: API REST (por definir con el equipo). | G95: 26/12/26 al 01/01/27 | H95: =EQUIPO!$B$8 -> Jack | I95: Versión 3: Facturación, cobranzas y reportes
B96: 8 | D96: Número de seguimiento y estado de la queja (registrada, en atención o resuelta) | E96: Falta
B97: 8 | D97: El Departamento de Quejas responde y cierra la queja con la solución dada | E97: Falta
B98: 8 | D98: Notificación al socio en cada cambio de estado | E98: Falta
B99: 8 | C99: HU24 - Reportes y panel gerencial Como Gerente General quiero visualizar reportes e indicadores para tomar decisiones sobre la gestión del club. | D99: Panel con socios activos, embarcaciones y radas ocupadas | E99: Falta | F99: Angular, Bootstrap 5, SCSS. Gráficos: Chart.js (por confirmar). Datos: API REST (por definir con el equipo). | G99: 26/12/26 al 08/01/27 | H99: =EQUIPO!$B$8 -> Jack | I99: Versión 3: Facturación, cobranzas y reportes
B100: 8 | D100: Reporte de facturación y cobranzas por mes | E100: Falta
B101: 8 | D101: Reporte de morosidad y de quejas atendidas | E101: Falta
...

Sheet FASES
A1: FASES DE DESARROLLO
A3: Cada sprint dura 2 semanas, contadas desde el 19/09/26 (inicio del Sprint 1, Home page).
A5: Sprint | B5: Fechas | C5: Épica | D5: Objetivo del sprint | E5: Entregable / Hito | F5: Release
A6: 1 | B6: 19/09/26 al 02/10/26 | C6: Home Page y Base del Sistema Web | D6: Configurar el proyecto (Angular, Bootstrap, SCSS, Git/GitHub) y construir el Home page. | E6: Home page responsive publicado en la rama develop; repositorio con commits de todos los integrantes. | F6: Versión 1: Home page y acceso al sistema
A7: 2 | B7: 03/10/26 al 16/10/26 | C7: Acceso al Sistema y Roles de Usuario | D7: Implementar inicio de sesión y control de acceso por rol. | E7: Login funcional y menús por rol. | F7: Versión 1: Home page y acceso al sistema
A8: 3 | B8: 17/10/26 al 30/10/26 | C8: Inscripción y Aprobación de Socios | D8: Digitalizar la inscripción, verificación y aprobación de socios. | E8: Flujo completo de solicitud → verificación → aprobación/desaprobación. | F8: Versión 2: Socios, embarcaciones y salidas
A9: 4 | B9: 31/10/26 al 13/11/26 | C9: Embarcaciones y Radas | D9: Registrar embarcaciones, verificarlas y asignar radas. | E9: Ficha de embarcación y asignación de rada. | F9: Versión 2: Socios, embarcaciones y salidas
A10: 5 | B10: 14/11/26 al 27/11/26 | C10: Salidas de Embarcaciones | D10: Gestionar permisos de salida y el registro de salidas y retornos. | E10: Solicitud, validación y registro de salidas. | F10: Versión 2: Socios, embarcaciones y salidas
A11: 6 | B11: 28/11/26 al 11/12/26 | C11: Servicios del Club y Facturación | D11: Registrar servicios adicionales y emitir la facturación mensual y diferida. | E11: Recibos mensuales con membresía, rada y servicios. | F11: Versión 3: Facturación, cobranzas y reportes
A12: 7 | B12: 12/12/26 al 25/12/26 | C12: Cobranzas y Retiro de Socios | D12: Registrar pagos, calcular intereses por mora y tramitar retiros con liquidación. | E12: Estado de cuenta, liquidación administrativa y baja de socio. | F12: Versión 3: Facturación, cobranzas y reportes
A13: 8 | B13: 26/12/26 al 08/01/27 | C13: Atención al Cliente y Reportes Gerenciales | D13: Gestionar quejas y ofrecer reportes para la gerencia; cierre y pruebas finales. | E13: Módulo de quejas, panel gerencial y versión final del sistema. | F13: Versión 3: Facturación, cobranzas y reportes

Sheet EQUIPO
A1: EQUIPO DEL PROYECTO
A3: Cómo usar esta hoja: escribe los datos de cada integrante en las celdas amarillas. Los nombres de la columna B se actualizan solos en PLANIFICACION y RESUMEN.
A5: N° | B5: Nombre completo | C5: Rol en el proyecto | D5: Usuario de GitHub | E5: Correo
A6: Ej. | B6: Ana Torres Quispe | C6: Scrum Master y desarrollador | D6: anatorres-dev | E6: ana.torres@correo.com
A7: 1 | B7: Jose Espinoza Rivadeneira | C7: Header, Footer y Hero (Home)
A8: 2 | B8: Jack | C8: Secciones informativas y Contacto (Home)
A12: Nota: el plan está repartido entre 2 integrantes (12 historias de usuario cada uno). En el Sprint 1 (Home page): Jose desarrolla Header, Footer y Hero (HU01-HU03); Jack desarrolla las secciones informativas y Contacto (HU04-HU05). Si el equipo cambia de tamaño, reasigna la columna "Recurso Responsable" en PLANIFICACION (lista desplegable).

Sheet RESUMEN
A1: RESUMEN DE AVANCE
A3: Se calcula automáticamente con la columna Estado de PLANIFICACION (cada fila = un criterio de aceptación).
A5: Avance por sprint
A6: Sprint | B6: Criterios totales | C6: Completado | D6: En proceso | E6: Falta | F6: % avance
A7: 1 | B7: =COUNTIF(PLANIFICACION!$B$6:$B$300,A7) -> 20 | C7: =COUNTIFS(PLANIFICACION!$B$6:$B$300,$A7,PLANIFICACION!$E$6:$E$300,"Completado") -> 16 | D7: =COUNTIFS(PLANIFICACION!$B$6:$B$300,$A7,PLANIFICACION!$E$6:$E$300,"En proceso") -> 3 | E7: =COUNTIFS(PLANIFICACION!$B$6:$B$300,$A7,PLANIFICACION!$E$6:$E$300,"Falta") -> 1 | F7: =IF(B7=0,0,C7/B7) -> 0.8
A8: 2 | B8: =COUNTIF(PLANIFICACION!$B$6:$B$300,A8) -> 8 | C8: =COUNTIFS(PLANIFICACION!$B$6:$B$300,$A8,PLANIFICACION!$E$6:$E$300,"Completado") -> 0 | D8: =COUNTIFS(PLANIFICACION!$B$6:$B$300,$A8,PLANIFICACION!$E$6:$E$300,"En proceso") -> 0 | E8: =COUNTIFS(PLANIFICACION!$B$6:$B$300,$A8,PLANIFICACION!$E$6:$E$300,"Falta") -> 8 | F8: =IF(B8=0,0,C8/B8) -> 0
A9: 3 | B9: =COUNTIF(PLANIFICACION!$B$6:$B$300,A9) -> 13 | C9: =COUNTIFS(PLANIFICACION!$B$6:$B$300,$A9,PLANIFICACION!$E$6:$E$300,"Completado") -> 0 | D9: =COUNTIFS(PLANIFICACION!$B$6:$B$300,$A9,PLANIFICACION!$E$6:$E$300,"En proceso") -> 0 | E9: =COUNTIFS(PLANIFICACION!$B$6:$B$300,$A9,PLANIFICACION!$E$6:$E$300,"Falta") -> 13 | F9: =IF(B9=0,0,C9/B9) -> 0
A10: 4 | B10: =COUNTIF(PLANIFICACION!$B$6:$B$300,A10) -> 12 | C10: =COUNTIFS(PLANIFICACION!$B$6:$B$300,$A10,PLANIFICACION!$E$6:$E$300,"Completado") -> 0 | D10: =COUNTIFS(PLANIFICACION!$B$6:$B$300,$A10,PLANIFICACION!$E$6:$E$300,"En proceso") -> 0 | E10: =COUNTIFS(PLANIFICACION!$B$6:$B$300,$A10,PLANIFICACION!$E$6:$E$300,"Falta") -> 12 | F10: =IF(B10=0,0,C10/B10) -> 0
A11: 5 | B11: =COUNTIF(PLANIFICACION!$B$6:$B$300,A11) -> 12 | C11: =COUNTIFS(PLANIFICACION!$B$6:$B$300,$A11,PLANIFICACION!$E$6:$E$300,"Completado") -> 0 | D11: =COUNTIFS(PLANIFICACION!$B$6:$B$300,$A11,PLANIFICACION!$E$6:$E$300,"En proceso") -> 0 | E11: =COUNTIFS(PLANIFICACION!$B$6:$B$300,$A11,PLANIFICACION!$E$6:$E$300,"Falta") -> 12 | F11: =IF(B11=0,0,C11/B11) -> 0
A12: 6 | B12: =COUNTIF(PLANIFICACION!$B$6:$B$300,A12) -> 12 | C12: =COUNTIFS(PLANIFICACION!$B$6:$B$300,$A12,PLANIFICACION!$E$6:$E$300,"Completado") -> 0 | D12: =COUNTIFS(PLANIFICACION!$B$6:$B$300,$A12,PLANIFICACION!$E$6:$E$300,"En proceso") -> 0 | E12: =COUNTIFS(PLANIFICACION!$B$6:$B$300,$A12,PLANIFICACION!$E$6:$E$300,"Falta") -> 12 | F12: =IF(B12=0,0,C12/B12) -> 0
A13: 7 | B13: =COUNTIF(PLANIFICACION!$B$6:$B$300,A13) -> 12 | C13: =COUNTIFS(PLANIFICACION!$B$6:$B$300,$A13,PLANIFICACION!$E$6:$E$300,"Completado") -> 0 | D13: =COUNTIFS(PLANIFICACION!$B$6:$B$300,$A13,PLANIFICACION!$E$6:$E$300,"En proceso") -> 0 | E13: =COUNTIFS(PLANIFICACION!$B$6:$B$300,$A13,PLANIFICACION!$E$6:$E$300,"Falta") -> 12 | F13: =IF(B13=0,0,C13/B13) -> 0
A14: 8 | B14: =COUNTIF(PLANIFICACION!$B$6:$B$300,A14) -> 8 | C14: =COUNTIFS(PLANIFICACION!$B$6:$B$300,$A14,PLANIFICACION!$E$6:$E$300,"Completado") -> 0 | D14: =COUNTIFS(PLANIFICACION!$B$6:$B$300,$A14,PLANIFICACION!$E$6:$E$300,"En proceso") -> 0 | E14: =COUNTIFS(PLANIFICACION!$B$6:$B$300,$A14,PLANIFICACION!$E$6:$E$300,"Falta") -> 8 | F14: =IF(B14=0,0,C14/B14) -> 0
A15: TOTAL | B15: =SUM(B7:B14) -> 97 | C15: =SUM(C7:C14) -> 16 | D15: =SUM(D7:D14) -> 3 | E15: =SUM(E7:E14) -> 78 | F15: =IF(B15=0,0,C15/B15) -> 0.16494845
A18: Historias de usuario por integrante
A19: Integrante | B19: HU asignadas | C19: HU en Sprint 1 | D19: % del total
A20: =EQUIPO!$B$7 -> Jose Espinoza Rivadeneira | B20: =COUNTIF(PLANIFICACION!$H$6:$H$300,A20) -> 12 | C20: =COUNTIFS(PLANIFICACION!$H$6:$H$300,A20,PLANIFICACION!$B$6:$B$300,1) -> 3 | D20: =IF($B$22=0,0,B20/$B$22) -> 0.5
A21: =EQUIPO!$B$8 -> Jack | B21: =COUNTIF(PLANIFICACION!$H$6:$H$300,A21) -> 12 | C21: =COUNTIFS(PLANIFICACION!$H$6:$H$300,A21,PLANIFICACION!$B$6:$B$300,1) -> 2 | D21: =IF($B$22=0,0,B21/$B$22) -> 0.5
A22: TOTAL | B22: =SUM(B20:B21) -> 24 | C22: =SUM(C20:C21) -> 5 | D22: =SUM(D20:D21) -> 1
